Metadata-Version: 2.1
Name: gonews
Version: 0.0.1
Summary: A simple to use CLI for viewing Google News top stories and searching for specific stories
Home-page: https://www.github.com/tannerburns/gonews
Author: Tanner Burns
Author-email: tjburns102@gmail.com
License: UNKNOWN
Platform: UNKNOWN
